pyubibot/__init__.py
pyubibot/channels.py
pyubibot/constants.py
test/__init__.py
test/test_channels.py
test/test_ubibot.py
pyubibot-0.0.4.dist-info/LICENSE
pyubibot-0.0.4.dist-info/METADATA
pyubibot-0.0.4.dist-info/WHEEL
pyubibot-0.0.4.dist-info/top_level.txt
pyubibot-0.0.4.dist-info/RECORD
