Metadata-Version: 2.1
Name: pyubibot
Version: 0.0.4
Summary: Python implementation for Ubibot APIs.
Home-page: https://github.com/dannytsang/pyubibot
Author: Danny Tsang
Author-email: danny@tsang.uk
Classifier: Programming Language :: Python :: 3
Classifier: License :: OSI Approved :: Apache Software License
Classifier: Operating System :: OS Independent
Requires-Python: >=3.8
License-File: LICENSE
